rolodex/__init__.py
rolodex/cli.py
rolodex/database.py
rolodex/db_load.py
rolodex/tui_editor.py
rolodex/utils.py
rolodex_cli-0.5.0.dist-info/licenses/LICENSE
rolodex_cli-0.5.0.dist-info/METADATA
rolodex_cli-0.5.0.dist-info/WHEEL
rolodex_cli-0.5.0.dist-info/entry_points.txt
rolodex_cli-0.5.0.dist-info/top_level.txt
rolodex_cli-0.5.0.dist-info/RECORD
