Metadata-Version: 2.4
Name: rolodex-cli
Version: 0.5.0
Summary: Simple rolodex DB utilities
Author: Darrien Rushing
License-Expression: MIT
Project-URL: Homepage, https://github.com/meddlin/rolodex
Requires-Python: >=3.11
License-File: LICENSE
Requires-Dist: linkify-it-py==2.0.3
Requires-Dist: markdown-it-py==4.0.0
Requires-Dist: mdit-py-plugins==0.5.0
Requires-Dist: mdurl==0.1.2
Requires-Dist: platformdirs==4.4.0
Requires-Dist: Pygments==2.19.2
Requires-Dist: rich==14.1.0
Requires-Dist: textual==6.1.0
Requires-Dist: typing_extensions==4.15.0
Requires-Dist: uc-micro-py==1.0.3
Provides-Extra: dev
Requires-Dist: pytest>=8.0; extra == "dev"
Dynamic: license-file
